qubesync/__init__.py
qubesync/client.py
qubesync/request_builder.py
qubesync-0.1.1.dist-info/licenses/LICENSE
qubesync-0.1.1.dist-info/METADATA
qubesync-0.1.1.dist-info/WHEEL
qubesync-0.1.1.dist-info/top_level.txt
qubesync-0.1.1.dist-info/RECORD
