Metadata-Version: 2.4
Name: qubesync
Version: 0.1.1
Summary: A Python library for QuickBooks Desktop / Enterprise integration via QubeSync API with intuitive DSL for building QBXML requests.
Author-email: QubeSync <support@qubesync.com>
License: MIT
Project-URL: Homepage, https://github.com/qubeintegrations/qube_sync_py
Project-URL: Documentation, https://docs.qubesync.com
Project-URL: Repository, https://github.com/qubeintegrations/qube_sync_py
Project-URL: Issues, https://github.com/qubeintegrations/qube_sync_py/issues
Keywords: quickbooks,qbxml,accounting,integration,api,dsl
Classifier: Development Status :: 4 - Beta
Classifier: Intended Audience :: Developers
Classifier: License :: OSI Approved :: MIT License
Classifier: Programming Language :: Python :: 3
Classifier: Programming Language :: Python :: 3.8
Classifier: Programming Language :: Python :: 3.9
Classifier: Programming Language :: Python :: 3.10
Classifier: Programming Language :: Python :: 3.11
Classifier: Programming Language :: Python :: 3.12
Classifier: Programming Language :: Python :: 3.13
Classifier: Topic :: Software Development :: Libraries :: Python Modules
License-File: LICENSE
Requires-Dist: requests
Dynamic: license-file
